scopyon/__init__.py
scopyon/config.py
scopyon/configbase.py
scopyon/constants.py
scopyon/effects.py
scopyon/epifm.py
scopyon/image.py
scopyon/io.py
scopyon/samples.py
scopyon/spot_detection.py
scopyon/spot_detection2.py
scopyon/catalog/dichroic_list.txt
scopyon/catalog/emission_list.txt
scopyon/catalog/excitation_list.txt
scopyon/catalog/fluorophorelist.txt
scopyon/catalog/detector/CCD.csv
scopyon/catalog/detector/EMCCD-Color.csv
scopyon/catalog/detector/EMCCD.csv
scopyon/catalog/detector/PMT.csv
scopyon/catalog/detector/RNDist_F40.csv
scopyon/catalog/detector/sCMOS-I.csv
scopyon/catalog/detector/sCMOS-II.csv
scopyon/catalog/dichroic/365DCLP.csv
scopyon/catalog/dichroic/380DCLP.csv
scopyon/catalog/dichroic/400DCLP.csv
scopyon/catalog/dichroic/420DCLP.csv
scopyon/catalog/dichroic/425DCLP.csv
scopyon/catalog/dichroic/425dcxr.csv
scopyon/catalog/dichroic/440DCLP.csv
scopyon/catalog/dichroic/440dcxr.csv
scopyon/catalog/dichroic/455DCLP.csv
scopyon/catalog/dichroic/460DCLP.csv
scopyon/catalog/dichroic/470dcxr.csv
scopyon/catalog/dichroic/470dcxru.csv
scopyon/catalog/dichroic/475dcxru.csv
scopyon/catalog/dichroic/485DCLP.csv
scopyon/catalog/dichroic/490DCLP.csv
scopyon/catalog/dichroic/495DCLP.csv
scopyon/catalog/dichroic/500DCLP.csv
scopyon/catalog/dichroic/500dcxr.csv
scopyon/catalog/dichroic/505DCLP.csv
scopyon/catalog/dichroic/505DCXT.csv
scopyon/catalog/dichroic/505dcxr.csv
scopyon/catalog/dichroic/505dcxru.csv
scopyon/catalog/dichroic/51000bs.csv
scopyon/catalog/dichroic/51001bs.csv
scopyon/catalog/dichroic/51002bs.csv
scopyon/catalog/dichroic/51003bs.csv
scopyon/catalog/dichroic/51004v2bs.csv
scopyon/catalog/dichroic/51005bs.csv
scopyon/catalog/dichroic/51006bs.csv
scopyon/catalog/dichroic/51007bs.csv
scopyon/catalog/dichroic/51008bs.csv
scopyon/catalog/dichroic/51009bs.csv
scopyon/catalog/dichroic/51010bs.csv
scopyon/catalog/dichroic/51011bs.csv
scopyon/catalog/dichroic/51012bs.csv
scopyon/catalog/dichroic/51013bs.csv
scopyon/catalog/dichroic/51014bs.csv
scopyon-0.1.12.dist-info/LICENSE
scopyon-0.1.12.dist-info/METADATA
scopyon-0.1.12.dist-info/WHEEL
scopyon-0.1.12.dist-info/top_level.txt
scopyon-0.1.12.dist-info/RECORD
