Metadata-Version: 2.1
Name: scopyon
Version: 0.1.12
Summary: Monte Carlo simulation toolkit for bioimaging systems
Home-page: https://github.com/ecell/scopyon
Author: Masaki Watabe
Author-email: masaki@riken.jp
Maintainer: Kazunari Kaizu
Maintainer-email: kaizu@riken.jp
License: BSD-3-Clause
Platform: UNKNOWN
Classifier: Development Status :: 3 - Alpha
Classifier: Programming Language :: Python :: 3
Classifier: Programming Language :: Python :: 3.6
Classifier: Programming Language :: Python :: 3 :: Only
Classifier: Topic :: Scientific/Engineering :: Bio-Informatics
Classifier: License :: OSI Approved :: BSD License
Requires-Python: >=3
Requires-Dist: numpy
Requires-Dist: scipy
Requires-Dist: matplotlib
